{
    "type": "minecraft:crafting_shaped",
    "pattern": [
        "WAS",
        "V I",
        "LMC"
    ],
    "key": {
        "W": {
            "item": "cataclysm:witherite_ingot"
        },
        "A": {
            "item": "cataclysm:ancient_metal_ingot"
        },
        "S": {
            "item": "cataclysm:essence_of_the_storm"
        },
        "I": {
            "item": "cataclysm:ignitium_ingot"
        },
        "C": {
            "item": "cataclysm:cursium_ingot"
        },
        "M": {
            "item": "cataclysm:monstrous_horn"
        },
        "L": {
            "item": "tcrcore:abyss_core"
        },
        "V": {
            "item": "tcrcore:void_core"
        }
    },
    "result": {
        "item": "tcrcore:proof_of_adventure",
        "count": 1
    }
}